FPC/__init__.py
fpc-0.89.dist-info/METADATA
fpc-0.89.dist-info/WHEEL
fpc-0.89.dist-info/top_level.txt
fpc-0.89.dist-info/RECORD
