Metadata-Version: 2.4
Name: FPC
Version: 0.89
Summary: Frank's Personal Conllection
Home-page: http://ff2.pw
Author: Frank
Author-email: luoziluojun@126.com
Maintainer: Frank
Maintainer-email: luoziluojun@126.com
License: BSD License
Platform: all
Classifier: Development Status :: 4 - Beta
Classifier: Operating System :: OS Independent
Classifier: Intended Audience :: Developers
Classifier: License :: OSI Approved :: BSD License
Classifier: Programming Language :: Python :: 3
Classifier: Topic :: Software Development :: Libraries
Dynamic: author
Dynamic: author-email
Dynamic: classifier
Dynamic: description
Dynamic: home-page
Dynamic: license
Dynamic: maintainer
Dynamic: maintainer-email
Dynamic: platform
Dynamic: summary
